LICENSE
README.md
setup.py
dungeon_maps/__init__.py
dungeon_maps/maps.py
dungeon_maps/utils.py
dungeon_maps.egg-info/PKG-INFO
dungeon_maps.egg-info/SOURCES.txt
dungeon_maps.egg-info/dependency_links.txt
dungeon_maps.egg-info/requires.txt
dungeon_maps.egg-info/top_level.txt
dungeon_maps/demos/__init__.py
dungeon_maps/demos/ego_flow/__init__.py
dungeon_maps/demos/ego_flow/run.py
dungeon_maps/demos/ego_flow/vis.py
dungeon_maps/demos/height_map/__init__.py
dungeon_maps/demos/height_map/run.py
dungeon_maps/demos/height_map/vis.py
dungeon_maps/demos/object_map/__init__.py
dungeon_maps/demos/object_map/run.py
dungeon_maps/demos/object_map/vis.py
dungeon_maps/demos/object_map_v2/__init__.py
dungeon_maps/demos/object_map_v2/run.py
dungeon_maps/demos/object_map_v2/vis.py
dungeon_maps/sim/__init__.py
dungeon_maps/sim/dungeon.py
dungeon_maps/sim/forest.py
dungeon_maps/sim/playground.py
dungeon_maps/sim/data/dungeon.fs
dungeon_maps/sim/data/dungeon.vs
dungeon_maps/sim/data/forest.fs
dungeon_maps/sim/data/forest.vs
dungeon_maps/sim/data/playground.fs
dungeon_maps/sim/data/playground.vs