Metadata-Version: 2.1
Name: dungeon-maps
Version: 0.0.3a1
Summary: A tiny PyTorch library for depth map manipulations
Home-page: https://github.com/Ending2015a/dungeon_map
Author: JoeHsiao
Author-email: joehsiao@gapp.nthu.edu.tw
License: MIT
Keywords: deep learning,computer vision,machine learning,robotics,depth map,point cloud,orthographic projection
Platform: UNKNOWN
Classifier: Development Status :: 2 - Pre-Alpha
Classifier: Intended Audience :: Science/Research
Classifier: Topic :: Scientific/Engineering :: Artificial Intelligence
Classifier: Topic :: Software Development :: Libraries :: Python Modules
Classifier: License :: OSI Approved :: MIT License
Classifier: Programming Language :: Python :: 3.6
Classifier: Programming Language :: Python :: 3.7
Classifier: Programming Language :: Python :: 3.8
Classifier: Programming Language :: Python :: 3.9
Requires-Python: >=3.6
Provides-Extra: sim
License-File: LICENSE
